{"nodes": [{"id": "users_coton_documents_personal_toki_crates_client_src_main_rs", "label": "main.rs", "file_type": "code", "source_file": "crates/client/src/main.rs", "source_location": "L1"}, {"id": "src_main_main", "label": "main()", "file_type": "code", "source_file": "crates/client/src/main.rs", "source_location": "L30"}, {"id": "result", "label": "Result", "file_type": "code", "source_file": "crates/client/src/main.rs", "source_location": "L30"}], "edges": [{"source": "users_coton_documents_personal_toki_crates_client_src_main_rs", "target": "egui", "relation": "imports_from", "confidence": "EXTRACTED", "source_file": "crates/client/src/main.rs", "source_location": "L25", "weight": 1.0, "context": "import"}, {"source": "users_coton_documents_personal_toki_crates_client_src_main_rs", "target": "envfilter", "relation": "imports_from", "confidence": "EXTRACTED", "source_file": "crates/client/src/main.rs", "source_location": "L26", "weight": 1.0, "context": "import"}, {"source": "users_coton_documents_personal_toki_crates_client_src_main_rs", "target": "tokiapp", "relation": "imports_from", "confidence": "EXTRACTED", "source_file": "crates/client/src/main.rs", "source_location": "L28", "weight": 1.0, "context": "import"}, {"source": "users_coton_documents_personal_toki_crates_client_src_main_rs", "target": "src_main_main", "relation": "contains", "confidence": "EXTRACTED", "source_file": "crates/client/src/main.rs", "source_location": "L30", "weight": 1.0}, {"source": "src_main_main", "target": "result", "relation": "references", "confidence": "EXTRACTED", "source_file": "crates/client/src/main.rs", "source_location": "L30", "weight": 1.0, "context": "return_type"}], "raw_calls": [{"caller_nid": "src_main_main", "callee": "with_env_filter", "is_member_call": true, "source_file": "/Users/coton/Documents/personal/toki/crates/client/src/main.rs", "source_location": "L36"}, {"caller_nid": "src_main_main", "callee": "unwrap_or_else", "is_member_call": true, "source_file": "/Users/coton/Documents/personal/toki/crates/client/src/main.rs", "source_location": "L37"}, {"caller_nid": "src_main_main", "callee": "install_default", "is_member_call": true, "source_file": "/Users/coton/Documents/personal/toki/crates/client/src/main.rs", "source_location": "L44"}, {"caller_nid": "src_main_main", "callee": "with_title", "is_member_call": true, "source_file": "/Users/coton/Documents/personal/toki/crates/client/src/main.rs", "source_location": "L51"}, {"caller_nid": "src_main_main", "callee": "with_resizable", "is_member_call": true, "source_file": "/Users/coton/Documents/personal/toki/crates/client/src/main.rs", "source_location": "L51"}, {"caller_nid": "src_main_main", "callee": "with_max_inner_size", "is_member_call": true, "source_file": "/Users/coton/Documents/personal/toki/crates/client/src/main.rs", "source_location": "L51"}, {"caller_nid": "src_main_main", "callee": "with_min_inner_size", "is_member_call": true, "source_file": "/Users/coton/Documents/personal/toki/crates/client/src/main.rs", "source_location": "L51"}, {"caller_nid": "src_main_main", "callee": "with_inner_size", "is_member_call": true, "source_file": "/Users/coton/Documents/personal/toki/crates/client/src/main.rs", "source_location": "L51"}, {"caller_nid": "src_main_main", "callee": "load_window_icon", "is_member_call": false, "source_file": "/Users/coton/Documents/personal/toki/crates/client/src/main.rs", "source_location": "L57"}, {"caller_nid": "src_main_main", "callee": "with_icon", "is_member_call": true, "source_file": "/Users/coton/Documents/personal/toki/crates/client/src/main.rs", "source_location": "L58"}, {"caller_nid": "src_main_main", "callee": "set_visuals", "is_member_call": true, "source_file": "/Users/coton/Documents/personal/toki/crates/client/src/main.rs", "source_location": "L101"}]}